easyeve/__init__.py
easyeve/main.py
easyeve-0.0.2.dist-info/METADATA
easyeve-0.0.2.dist-info/WHEEL
easyeve-0.0.2.dist-info/entry_points.txt
easyeve-0.0.2.dist-info/top_level.txt
easyeve-0.0.2.dist-info/zip-safe
easyeve-0.0.2.dist-info/RECORD
