Metadata-Version: 2.1
Name: easyeve
Version: 0.0.2
Summary: maiff tools
Home-page: UNKNOWN
Author: maiff
Author-email: xwt2101239@gmail.com
License: MIT
Keywords: maiff easyeve terminal
Platform: UNKNOWN
Requires-Dist: requests
